funlab/sched/__init__.py
funlab/sched/conf/plugin.toml
funlab/sched/conf/task.toml
funlab/sched/service.py
funlab/sched/task.py
funlab/sched/templates/args_dialog.html
funlab/sched/templates/tasks.html
funlab_sched-0.3.5.dist-info/entry_points.txt
funlab_sched-0.3.5.dist-info/LICENSE
funlab_sched-0.3.5.dist-info/METADATA
funlab_sched-0.3.5.dist-info/WHEEL
funlab_sched-0.3.5.dist-info/RECORD
