Metadata-Version: 2.1
Name: funlab-sched
Version: 0.3.5
Summary: A funlab-flaskr service plugin provide task scheduling, using APScheduler.
Home-page: https://github.com/sunnylin13/funlab-sched
Author: sunny
Author-email: 013.lin@gmail.com
Requires-Python: >=3.11,<4.0
Classifier: Programming Language :: Python :: 3
Classifier: Programming Language :: Python :: 3.11
Classifier: Programming Language :: Python :: 3.12
Requires-Dist: apscheduler (>=3.10.1,<4.0.0)
Requires-Dist: flask-wtf (>=1.2.1,<2.0.0)
Requires-Dist: funlab-flaskr (>=0.3.1,<0.4.0)
Project-URL: Repository, https://github.com/sunnylin13/funlab-sched
